axiom/__data.py
axiom/__import.py
axiom/__init__.py
axiom/__main__.py
axiom/__type.py
axiom/common.py
axiom/data_reader.py
axiom/info.py
axiom/settings.py
axiom/documentation/index.py
axiom/example/simple_add/add_by_config.py
axiom/example/simple_add/add_func.py
axiom/example/simple_add/add_one_and_two.py
axiom/example/simple_add/add_one_func.py
axiom/example/simple_add/just_test.py
reaxiom-0.1.0.dist-info/METADATA
reaxiom-0.1.0.dist-info/WHEEL
reaxiom-0.1.0.dist-info/licenses/LICENSE
reaxiom-0.1.0.dist-info/RECORD
